availability.py
availability-0.0.3.dist-info/METADATA
availability-0.0.3.dist-info/WHEEL
availability-0.0.3.dist-info/licenses/LICENSE
availability-0.0.3.dist-info/RECORD
