Metadata-Version: 2.1
Name: availability
Version: 0.0.3
Summary: A custom python type for working with sparse ranges of padded timedate intervals
Project-URL: Homepage, https://github.com/Calendim/availability
Project-URL: Bug Tracker, https://github.com/Calendim/availability/issues
Author-email: Paul Stenius <stenius@gmail.com>
License-File: LICENSE
Classifier: License :: OSI Approved :: MIT License
Classifier: Operating System :: OS Independent
Classifier: Programming Language :: Python :: 3
Requires-Python: >=3.9
